multiselectfield/__init__.py
multiselectfield/apps.py
multiselectfield/utils.py
multiselectfield/validators.py
multiselectfield/db/__init__.py
multiselectfield/db/fields.py
multiselectfield/forms/__init__.py
multiselectfield/forms/fields.py
multiselectfield/locale/es/LC_MESSAGES/django.mo
multiselectfield/locale/es/LC_MESSAGES/django.po
fork_django_multiselectfield-0.1.0.dist-info/COPYING.LGPLv3
fork_django_multiselectfield-0.1.0.dist-info/METADATA
fork_django_multiselectfield-0.1.0.dist-info/WHEEL
fork_django_multiselectfield-0.1.0.dist-info/top_level.txt
fork_django_multiselectfield-0.1.0.dist-info/RECORD
