Metadata-Version: 2.1
Name: fork-django-multiselectfield
Version: 0.1.0
Summary: Django multiple select field
Home-page: https://github.com/son-eoh/django-multiselectfield
Author: Son (fork from Pablo Martin)
Author-email: son.lg@eoh.io
License: LGPL 3
Keywords: django,multiple,select,field,choices
Classifier: Development Status :: 4 - Beta
Classifier: Framework :: Django
Classifier: License :: OSI Approved :: GNU Library or Lesser General Public License (LGPL)
Classifier: Programming Language :: Python :: 2
Classifier: Programming Language :: Python :: 2.6
Classifier: Programming Language :: Python :: 2.7
Classifier: Programming Language :: Python :: 3
Classifier: Programming Language :: Python :: 3.3
Classifier: Programming Language :: Python :: 3.4
Classifier: Programming Language :: Python :: 3.5
Classifier: Programming Language :: Python :: 3.6
Classifier: Programming Language :: Python :: 3.7
Classifier: Programming Language :: Python :: 3.8
License-File: COPYING.LGPLv3
Requires-Dist: django (>=1.4)
